aiosenseme/__init__.py
aiosenseme/device.py
aiosenseme/discovery.py
aiosenseme/version.py
aiosenseme/scripts/__init__.py
aiosenseme/scripts/commandline.py
aiosenseme-0.6.1.dist-info/LICENSE
aiosenseme-0.6.1.dist-info/METADATA
aiosenseme-0.6.1.dist-info/WHEEL
aiosenseme-0.6.1.dist-info/entry_points.txt
aiosenseme-0.6.1.dist-info/top_level.txt
aiosenseme-0.6.1.dist-info/RECORD
