Metadata-Version: 2.1
Name: aiosenseme
Version: 0.6.1
Summary: SenseME by Big Ass Fans asynchronous Python library
Home-page: https://github.com/mikelawrence/aiosenseme
Author: mikelawrence, bdraco
Author-email: mikealawr@gmail.com, bdraco@gmail.com
License: GPL3
Keywords: Haiku HaikuHome SenseME fan home automation BigAssFans
Platform: UNKNOWN
Classifier: Development Status :: 3 - Alpha
Classifier: Intended Audience :: Developers
Classifier: Framework :: AsyncIO
Classifier: Programming Language :: Python :: 3.7
Classifier: Programming Language :: Python :: 3.8
Classifier: Programming Language :: Python :: 3.9
Classifier: Programming Language :: Python :: 3.10
Classifier: Topic :: Home Automation
Requires-Python: >=3.7
License-File: LICENSE
Requires-Dist: ifaddr (>=0.1.7)
